eldar/__init__.py
eldar/entry.py
eldar/index.py
eldar/indexops.py
eldar/operators.py
eldar/query.py
eldar/regex.py
eldar/trie.py
eldar-0.0.8.dist-info/LICENSE.txt
eldar-0.0.8.dist-info/METADATA
eldar-0.0.8.dist-info/WHEEL
eldar-0.0.8.dist-info/top_level.txt
eldar-0.0.8.dist-info/RECORD
