Metadata-Version: 2.1
Name: eldar
Version: 0.0.8
Summary: Boolean text search in Python
Home-page: https://github.com/kerighan/eldar
Author: Maixent Chenebaux
Author-email: max.chbx@gmail.com
License: UNKNOWN
Platform: UNKNOWN
Classifier: Programming Language :: Python :: 3.7
Classifier: Operating System :: OS Independent
